README.rst
setup.py
sphinxcontrib/__init__.py
sphinxcontrib/jsx.py
sphinxcontrib_jsx.egg-info/PKG-INFO
sphinxcontrib_jsx.egg-info/SOURCES.txt
sphinxcontrib_jsx.egg-info/dependency_links.txt
sphinxcontrib_jsx.egg-info/namespace_packages.txt
sphinxcontrib_jsx.egg-info/not-zip-safe
sphinxcontrib_jsx.egg-info/requires.txt
sphinxcontrib_jsx.egg-info/top_level.txt