Metadata-Version: 1.1
Name: sphinxcontrib-jsx
Version: 0.2.0
Summary: Sphinx JSX directive extension
Home-page: https://github.com/prometheusresearch/sphinxcontrib-jsx
Author: Prometheus Research, LLC
Author-email: UNKNOWN
License: BSD
Platform: any
Classifier: Development Status :: 4 - Beta
Classifier: Environment :: Console
Classifier: Environment :: Web Environment
Classifier: Intended Audience :: Developers
Classifier: License :: OSI Approved :: BSD License
Classifier: Operating System :: OS Independent
Classifier: Programming Language :: Python
Classifier: Topic :: Documentation
Classifier: Topic :: Utilities
